st_file_upload_ven/__init__.py
st_file_upload_ven/frontend/build/asset-manifest.json
st_file_upload_ven/frontend/build/bootstrap.min.css
st_file_upload_ven/frontend/build/index.html
st_file_upload_ven/frontend/build/precache-manifest.53e220aa4ead4886e36fd641fc1e2083.js
st_file_upload_ven/frontend/build/service-worker.js
st_file_upload_ven/frontend/build/static/css/main.239f2e9a.chunk.css
st_file_upload_ven/frontend/build/static/css/main.239f2e9a.chunk.css.map
st_file_upload_ven/frontend/build/static/js/2.740fea40.chunk.js
st_file_upload_ven/frontend/build/static/js/2.740fea40.chunk.js.LICENSE.txt
st_file_upload_ven/frontend/build/static/js/2.740fea40.chunk.js.map
st_file_upload_ven/frontend/build/static/js/main.cbf68461.chunk.js
st_file_upload_ven/frontend/build/static/js/main.cbf68461.chunk.js.map
st_file_upload_ven/frontend/build/static/js/runtime-main.44d30fc2.js
st_file_upload_ven/frontend/build/static/js/runtime-main.44d30fc2.js.map
streamlit_file_upload_ven-6.0.1.dist-info/LICENSE
streamlit_file_upload_ven-6.0.1.dist-info/METADATA
streamlit_file_upload_ven-6.0.1.dist-info/WHEEL
streamlit_file_upload_ven-6.0.1.dist-info/top_level.txt
streamlit_file_upload_ven-6.0.1.dist-info/RECORD
