Metadata-Version: 2.1
Name: streamlit-file-upload-ven
Version: 6.0.1
Home-page: 
Author: 
Author-email: 
Requires-Python: >=3.6
License-File: LICENSE
Requires-Dist: streamlit (>=0.63)
